process_tracker/__init__.py
process_tracker/cli.py
process_tracker/extract_tracker.py
process_tracker/location_tracker.py
process_tracker/process_tracker.py
process_tracker/models/__init__.py
process_tracker/models/actor.py
process_tracker/models/capacity.py
process_tracker/models/contact.py
process_tracker/models/extract.py
process_tracker/models/model_base.py
process_tracker/models/process.py
process_tracker/models/schedule.py
process_tracker/models/source.py
process_tracker/models/system.py
process_tracker/models/tool.py
process_tracker/utilities/__init__.py
process_tracker/utilities/aws_utilities.py
process_tracker/utilities/data_store.py
process_tracker/utilities/logging.py
process_tracker/utilities/settings.py
process_tracker/utilities/utilities.py
tests/__init__.py
tests/conftest.py
tests/test_cli.py
tests/test_extract_tracker.py
tests/test_location_tracker.py
tests/test_process_tracker.py
tests/test_process_tracker_pytest.py
tests/utilities/__init__.py
tests/utilities/test_aws_utilities.py
tests/utilities/test_settings_manager.py
tests/utilities/test_utilities.py
processtracker-0.9.0.dist-info/LICENSE.txt
processtracker-0.9.0.dist-info/METADATA
processtracker-0.9.0.dist-info/WHEEL
processtracker-0.9.0.dist-info/entry_points.txt
processtracker-0.9.0.dist-info/top_level.txt
processtracker-0.9.0.dist-info/RECORD
