Metadata-Version: 2.1
Name: processtracker
Version: 0.9.0
Summary: A framework for managing data integration processes and their data
Home-page: https://github.com/opendataalex/process_tracker_python
Author: Alex Meadows
Author-email: alexmeadows@bluefiredatasolutions.com
License: UNKNOWN
Platform: UNKNOWN
Classifier: Programming Language :: Python :: 3
Classifier: License :: OSI Approved :: GNU General Public License v3 (GPLv3)
Classifier: Operating System :: OS Independent
Classifier: Environment :: Console
Classifier: Environment :: Plugins
Classifier: Intended Audience :: Developers
Classifier: Natural Language :: English
Classifier: Topic :: Software Development
Requires-Dist: boto3 (>=1.9.150)
Requires-Dist: Click (>=7.0)
Requires-Dist: cx-oracle (>=7.1.3)
Requires-Dist: google-compute-engine (>=2.8.13)
Requires-Dist: psycopg2-binary (>=2.8.2)
Requires-Dist: pymysql (>=0.9.3)
Requires-Dist: pymssql (<3.0)
Requires-Dist: python-dateutil (>=2.8.0)
Requires-Dist: snowflake-sqlalchemy (>=1.1.13)
Requires-Dist: sqlalchemy (>=1.3.3)
Requires-Dist: sqlalchemy-utils (>=0.33.11)
